fromto/__init__.py
fromto/exeptions.py
fromto/fromto.py
fromto/utils.py
fromto-1.0.0.dist-info/LICENSE
fromto-1.0.0.dist-info/METADATA
fromto-1.0.0.dist-info/WHEEL
fromto-1.0.0.dist-info/top_level.txt
fromto-1.0.0.dist-info/RECORD
