Metadata-Version: 2.1
Name: fromto
Version: 1.0.0
Summary: Package for performing translation operations between Karakalpak and other 204 languages through the from-to.uz site
Author: Turdıbek Jumabaev
Author-email: <turdibekjumabaev05@gmail.com>
Keywords: karakalpak,fromto,translator
Classifier: Programming Language :: Python :: 3
Classifier: Operating System :: Unix
Classifier: Operating System :: MacOS :: MacOS X
Classifier: Operating System :: Microsoft :: Windows
License-File: LICENSE
Requires-Dist: requests
